{"stats":{"minecraft:used":{"minecraft:nether_brick_fence":2,"minecraft:iron_bars":2,"minecraft:enchanting_table":3,"minecraft:stone_sword":708,"minecraft:iron_shovel":416,"minecraft:flint_and_steel":25,"minecraft:dispenser":43,"minecraft:ladder":101,"minecraft:chest":24,"minecraft:spruce_planks":74,"minecraft:iron_sword":270,"minecraft:nether_wart":464,"minecraft:cooked_salmon":11,"minecraft:rotten_flesh":7,"minecraft:netherrack":59,"minecraft:oak_door":2,"minecraft:torch":1090,"minecraft:soul_sand":127,"minecraft:dirt":186,"minecraft:hopper":1,"minecraft:nether_bricks":2,"minecraft:carrot":78,"minecraft:spruce_fence":1,"minecraft:tuff":7,"minecraft:granite":7,"minecraft:spruce_boat":1,"minecraft:bookshelf":1,"minecraft:iron_axe":389,"minecraft:basalt":1,"minecraft:sweet_berries":42,"minecraft:furnace":18,"minecraft:beetroot_seeds":78,"minecraft:minecart":1,"minecraft:potato":130,"minecraft:cobbled_deepslate":142,"minecraft:pointed_dripstone":5,"minecraft:wheat_seeds":518,"minecraft:water_bucket":2,"minecraft:diorite":14,"minecraft:cobblestone_stairs":114,"minecraft:spruce_door":2,"minecraft:stone_pickaxe":402,"minecraft:oak_planks":1,"minecraft:baked_potato":169,"minecraft:wooden_pickaxe":8,"minecraft:spruce_sign":12,"minecraft:rail":1,"minecraft:crafting_table":10,"minecraft:white_bed":1,"minecraft:dripstone_block":9,"minecraft:cake":1,"minecraft:spruce_log":3,"minecraft:diamond_pickaxe":1888,"minecraft:bread":10,"minecraft:iron_pickaxe":3124,"minecraft:spruce_sapling":6,"minecraft:gravel":3,"minecraft:stone_axe":131,"minecraft:fishing_rod":48,"minecraft:cobblestone":123,"minecraft:white_banner":1,"minecraft:bucket":3},"minecraft:crafted":{"minecraft:oak_door":3,"minecraft:oak_planks":64,"minecraft:coal":9,"minecraft:fishing_rod":2,"minecraft:leather_boots":1,"minecraft:furnace":18,"minecraft:cobblestone_stairs":120,"minecraft:stone":328,"minecraft:bone_meal":24,"minecraft:spruce_fence":3,"minecraft:nether_brick":48,"minecraft:bookshelf":1,"minecraft:raw_copper_block":1174,"minecraft:flint_and_steel":1,"minecraft:iron_bars":16,"minecraft:quartz_block":3,"minecraft:hopper":1,"minecraft:bow":30,"minecraft:raw_copper":2176,"minecraft:iron_axe":2,"minecraft:ladder":138,"minecraft:stone_pickaxe":3,"minecraft:chest":24,"minecraft:copper_block":476,"minecraft:spruce_boat":3,"minecraft:redstone_block":164,"minecraft:minecart":1,"minecraft:golden_boots":2,"minecraft:coal_block":48,"minecraft:diamond_sword":2,"minecraft:spruce_sign":12,"minecraft:crafting_table":9,"minecraft:spruce_planks":640,"minecraft:enchanting_table":1,"minecraft:wooden_pickaxe":1,"minecraft:baked_potato":185,"minecraft:iron_sword":2,"minecraft:spruce_door":3,"minecraft:nether_bricks":6,"minecraft:cooked_salmon":11,"minecraft:copper_ingot":4313,"minecraft:nether_brick_fence":6,"minecraft:leather_helmet":1,"minecraft:stone_axe":1,"minecraft:bread":12,"minecraft:air":0,"minecraft:dispenser":5,"minecraft:white_wool":3,"minecraft:book":4,"minecraft:paper":12,"minecraft:diamond_pickaxe":2,"minecraft:stick":648,"minecraft:iron_ingot":839,"minecraft:leather_chestplate":1,"minecraft:iron_pickaxe":14,"minecraft:iron_block":61,"minecraft:stone_sword":11,"minecraft:iron_shovel":1,"minecraft:gold_ingot":266,"minecraft:white_bed":1,"minecraft:torch":1068,"minecraft:lapis_lazuli":360,"minecraft:lapis_block":155},"minecraft:broken":{"minecraft:golden_helmet":1,"minecraft:iron_shovel":1,"minecraft:golden_boots":1,"minecraft:stone_sword":4,"minecraft:leather_leggings":2,"minecraft:chainmail_helmet":1,"minecraft:leather_chestplate":1,"minecraft:stone_pickaxe":4,"minecraft:chainmail_chestplate":1,"minecraft:iron_axe":1,"minecraft:stone_axe":1,"minecraft:leather_boots":1,"minecraft:iron_sword":1,"minecraft:iron_pickaxe":9},"minecraft:dropped":{"minecraft:spawner":1,"minecraft:enchanted_book":1,"minecraft:wheat_seeds":473,"minecraft:baked_potato":1,"minecraft:cobblestone":15,"minecraft:stick":4,"minecraft:flint":2,"minecraft:dirt":2,"minecraft:raw_copper_block":14,"minecraft:diorite":7,"minecraft:bone":1,"minecraft:stone_sword":5,"minecraft:cobbled_deepslate":15,"minecraft:raw_copper":24,"minecraft:wheat":1,"minecraft:pointed_dripstone":18,"minecraft:firework_star":3,"minecraft:potato":1,"minecraft:spruce_planks":93,"minecraft:diamond_pickaxe":1,"minecraft:andesite":4,"minecraft:arrow":1},"minecraft:mined":{"minecraft:nether_gold_ore":3,"minecraft:diamond_ore":4,"minecraft:tuff":15,"minecraft:spruce_planks":1,"minecraft:deepslate_diamond_ore":9,"minecraft:oak_door":2,"minecraft:obsidian":55,"minecraft:granite":60,"minecraft:grass_block":17,"minecraft:crimson_roots":1,"minecraft:soul_soil":7,"minecraft:spruce_leaves":108,"minecraft:nether_wart":464,"minecraft:tall_seagrass":5,"minecraft:redstone_ore":12,"minecraft:spruce_sapling":1,"minecraft:carrots":78,"minecraft:iron_ore":204,"minecraft:fire":2,"minecraft:cobbled_deepslate":23,"minecraft:andesite":56,"minecraft:stripped_spruce_log":1,"minecraft:pumpkin":2,"minecraft:deepslate_lapis_ore":50,"minecraft:potatoes":114,"minecraft:pointed_dripstone":22,"minecraft:deepslate_iron_ore":162,"minecraft:rail":1,"minecraft:stone":1317,"minecraft:deepslate_redstone_ore":199,"minecraft:soul_sand":127,"minecraft:basalt":5,"minecraft:crafting_table":1,"minecraft:torch":7,"minecraft:chest":2,"minecraft:spruce_wall_sign":2,"minecraft:nether_quartz_ore":47,"minecraft:copper_ore":1186,"minecraft:cobblestone":32,"minecraft:deepslate_coal_ore":5,"minecraft:lapis_ore":23,"minecraft:deepslate_gold_ore":108,"minecraft:sugar_cane":58,"minecraft:oak_planks":2,"minecraft:diorite":117,"minecraft:wall_torch":7,"minecraft:spruce_sign":1,"minecraft:deepslate_copper_ore":348,"minecraft:seagrass":5,"minecraft:cactus":23,"minecraft:sweet_berry_bush":2,"minecraft:wheat":498,"minecraft:spruce_log":490,"minecraft:birch_leaves":1,"minecraft:grass":1,"minecraft:coal_ore":356,"minecraft:oak_log":18,"minecraft:beetroots":78,"minecraft:gravel":107,"minecraft:dripstone_block":36,"minecraft:dirt":230,"minecraft:cobweb":18,"minecraft:dispenser":1,"minecraft:netherrack":175,"minecraft:gold_ore":22,"minecraft:oak_leaves":9,"minecraft:deepslate":700,"minecraft:fern":1},"minecraft:custom":{"minecraft:mob_kills":1375,"minecraft:animals_bred":9,"minecraft:inspect_hopper":10,"minecraft:interact_with_crafting_table":119,"minecraft:leave_game":15,"minecraft:time_since_death":1130480,"minecraft:climb_one_cm":226850,"minecraft:sprint_one_cm":2275648,"minecraft:walk_one_cm":2581913,"minecraft:drop":49,"minecraft:talked_to_villager":1,"minecraft:play_time":1130480,"minecraft:sneak_time":42100,"minecraft:walk_under_water_one_cm":131001,"minecraft:boat_one_cm":834060,"minecraft:jump":16816,"minecraft:interact_with_blast_furnace":6,"minecraft:walk_on_water_one_cm":100936,"minecraft:enchant_item":9,"minecraft:total_world_time":1130480,"minecraft:interact_with_furnace":651,"minecraft:sleep_in_bed":6,"minecraft:time_since_rest":20373,"minecraft:open_enderchest":1,"minecraft:damage_taken":10371,"minecraft:minecart_one_cm":14683,"minecraft:damage_dealt":31840,"minecraft:swim_one_cm":155315,"minecraft:fly_one_cm":3085114,"minecraft:open_chest":996,"minecraft:crouch_one_cm":105816,"minecraft:fish_caught":39,"minecraft:fall_one_cm":514829,"minecraft:inspect_dispenser":196},"minecraft:killed":{"minecraft:witch":9,"minecraft:spider":5,"minecraft:slime":46,"minecraft:phantom":1,"minecraft:skeleton":444,"minecraft:chicken":1,"minecraft:zombie_villager":9,"minecraft:salmon":11,"minecraft:creeper":401,"minecraft:zombie":439,"minecraft:glow_squid":3,"minecraft:enderman":1},"minecraft:picked_up":{"minecraft:wheat":421,"minecraft:crafting_table":1,"minecraft:firework_star":29,"minecraft:nether_wart":1132,"minecraft:leather_leggings":1,"minecraft:enchanted_book":1,"minecraft:string":24,"minecraft:raw_copper":14237,"minecraft:soul_soil":6,"minecraft:pufferfish":7,"minecraft:beetroot":71,"minecraft:gold_nugget":28,"minecraft:cobbled_deepslate":872,"minecraft:spruce_planks":91,"minecraft:minecart":1,"minecraft:chest":2,"minecraft:sugar_cane":110,"minecraft:phantom_membrane":1,"minecraft:stick":27,"minecraft:raw_iron":842,"minecraft:oak_door":2,"minecraft:torch":30,"minecraft:cake":2,"minecraft:pointed_dripstone":45,"minecraft:diorite":134,"minecraft:carrot":230,"minecraft:redstone":1594,"minecraft:stone_sword":1,"minecraft:arrow":46,"minecraft:cactus":39,"minecraft:rotten_flesh":38,"minecraft:beetroot_seeds":209,"minecraft:obsidian":93,"minecraft:cod":21,"minecraft:rail":2,"minecraft:cobblestone":1678,"minecraft:enchanting_table":3,"minecraft:leather_chestplate":1,"minecraft:basalt":8,"minecraft:glow_ink_sac":9,"minecraft:andesite":62,"minecraft:salmon":23,"minecraft:leather":128,"minecraft:potato":357,"minecraft:flint":10,"minecraft:tuff":18,"minecraft:oak_log":18,"minecraft:gunpowder":16,"minecraft:lapis_lazuli":1180,"minecraft:dirt":245,"minecraft:white_banner":2,"minecraft:spawner":7,"minecraft:bone":64,"minecraft:bow":9,"minecraft:wheat_seeds":1222,"minecraft:raw_gold":338,"minecraft:iron_ingot":1,"minecraft:soul_sand":127,"minecraft:oak_planks":1,"minecraft:pumpkin":2,"minecraft:sweet_berries":42,"minecraft:quartz":54,"minecraft:dripstone_block":35,"minecraft:poisonous_potato":1,"minecraft:gravel":109,"minecraft:stripped_spruce_log":1,"minecraft:spruce_sapling":28,"minecraft:spruce_log":496,"minecraft:spider_eye":1,"minecraft:spruce_door":1,"minecraft:leather_helmet":1,"minecraft:dispenser":38,"minecraft:slime_ball":40,"minecraft:diamond":26,"minecraft:spruce_boat":1,"minecraft:granite":42,"minecraft:bone_meal":1,"minecraft:spruce_sign":3,"minecraft:bread":4,"minecraft:baked_potato":1,"minecraft:netherrack":191,"minecraft:coal":727,"minecraft:ender_pearl":1,"minecraft:diamond_pickaxe":1}},"DataVersion":3120}